pyvolve/__init__.py
pyvolve/empirical_matrices.py
pyvolve/evolver.py
pyvolve/genetics.py
pyvolve/matrix_builder.py
pyvolve/model.py
pyvolve/newick.py
pyvolve/parameters_sanity.py
pyvolve/partition.py
pyvolve/state_freqs.py
tests/__init__.py
tests/evolver_test.py
tests/matrix_builder_test.py
tests/model_test.py
tests/newick_test.py
tests/parameters_sanity_test.py
tests/state_freqs_test.py
tests/evolFiles/expected_sim_seed.fasta
tests/evolFiles/single_part_no_het_rates.txt
tests/evolFiles/two_part_no_het_rates.txt
tests/freqFiles/testFreq_amino_aln.fasta
tests/freqFiles/testFreq_codon_aln.fasta
Pyvolve-1.1.0.dist-info/LICENSE.txt
Pyvolve-1.1.0.dist-info/METADATA
Pyvolve-1.1.0.dist-info/WHEEL
Pyvolve-1.1.0.dist-info/top_level.txt
Pyvolve-1.1.0.dist-info/RECORD
