Metadata-Version: 2.1
Name: Pyvolve
Version: 1.1.0
Summary: Sequence simulation along phylogenies according to continuous-time Markov models
Home-page: https://github.com/sjspielman/pyvolve
Author: Stephanie J. Spielman
Author-email: spielman@rowan.edu
License: UNKNOWN
Download-URL: https://github.com/sjspielman/pyvolve/tarball/1.1.0
Platform: Tested on Mac OS X.
Requires-Dist: numpy (>=1.20.0)
Requires-Dist: scipy
Requires-Dist: Biopython
